pylibgeohash.cpython-35m-x86_64-linux-gnu.so
pylibgeohash-0.2.2.dist-info/LICENSE
pylibgeohash-0.2.2.dist-info/METADATA
pylibgeohash-0.2.2.dist-info/WHEEL
pylibgeohash-0.2.2.dist-info/top_level.txt
pylibgeohash-0.2.2.dist-info/RECORD
